LICENCE.txt
MANIFEST.in
README.rst
setup.cfg
setup.py
py_css_styleguide/__init__.py
py_css_styleguide/exceptions.py
py_css_styleguide/logger.py
py_css_styleguide/model.py
py_css_styleguide/nomenclature.py
py_css_styleguide/parser.py
py_css_styleguide/serializer.py
py_css_styleguide.egg-info/PKG-INFO
py_css_styleguide.egg-info/SOURCES.txt
py_css_styleguide.egg-info/dependency_links.txt
py_css_styleguide.egg-info/entry_points.txt
py_css_styleguide.egg-info/requires.txt
py_css_styleguide.egg-info/top_level.txt
py_css_styleguide.egg-info/zip-safe
py_css_styleguide/cli/__init__.py
py_css_styleguide/cli/entrypoint.py
py_css_styleguide/cli/greet.py
py_css_styleguide/cli/parse.py
py_css_styleguide/cli/version.py
py_css_styleguide/django/__init__.py
py_css_styleguide/django/mixin.py
py_css_styleguide/django/views.py
py_css_styleguide/scss/dartsass/_styleguide_helpers.scss
py_css_styleguide/scss/libsass/_styleguide_helpers.scss
sandbox/settings/__init__.py
sandbox/settings/base.py
sandbox/settings/demo.py
sandbox/settings/tests.py